dm/__init__.py
dm/cloudtrailsdk/__init__.py
dm/cloudtrailsdk/__version__.py
dm/cloudtrailsdk/execptions.py
dm/cloudtrailsdk/client/__init__.py
dm/cloudtrailsdk/client/tracker.py
dm/cloudtrailsdk/decorators/__init__.py
dm/cloudtrailsdk/decorators/api_gateway_tracker.py
dm/cloudtrailsdk/decorators/custom_tracker.py
dm/cloudtrailsdk/decorators/exception_tracker.py
dm/cloudtrailsdk/middleware/__init__.py
dm/cloudtrailsdk/model/__init__.py
dm/cloudtrailsdk/model/event.py
dm/cloudtrailsdk/utils/__init__.py
dm/cloudtrailsdk/utils/functions.py
Datamart_AWS_CloudTrails_SDK-1.1.0.dist-info/LICENSE
Datamart_AWS_CloudTrails_SDK-1.1.0.dist-info/METADATA
Datamart_AWS_CloudTrails_SDK-1.1.0.dist-info/WHEEL
Datamart_AWS_CloudTrails_SDK-1.1.0.dist-info/top_level.txt
Datamart_AWS_CloudTrails_SDK-1.1.0.dist-info/RECORD
