Metadata-Version: 2.1
Name: Datamart-AWS-CloudTrails-SDK
Version: 1.1.0
Summary: AWS Python CloudTrails SDK for Logs
Home-page: https://bitbucket.org/elasbit/dm-cloudtrails-sdk-py
Author: Yaisel Hurtado, Raydel Miranda, Yordano Gonzalez
Author-email: hurta2yaisel@gmail.com, raydel.miranda.gomez@gmail.com, yorda891216@gmail.com
License: UNKNOWN
Platform: UNKNOWN
Classifier: Intended Audience :: Developers
Classifier: Programming Language :: Python :: 2.7
Classifier: Programming Language :: Python :: 3.4
Classifier: Programming Language :: Python :: 3.5
Classifier: Programming Language :: Python :: 3.6
Classifier: Programming Language :: Python :: 3.7
Classifier: Operating System :: OS Independent
Requires-Python: >=2.7, !=3.0.*, !=3.1.*, !=3.2.*, !=3.3.*, <3.8
Requires-Dist: boto3 (==1.10.13)
